donnes_des_sous_nawel/__init__.py
donnes_des_sous_nawel/banque.py
donnes_des_sous_nawel-0.1.1.dist-info/WHEEL
donnes_des_sous_nawel-0.1.1.dist-info/entry_points.txt
donnes_des_sous_nawel-0.1.1.dist-info/METADATA
donnes_des_sous_nawel-0.1.1.dist-info/RECORD
