Metadata-Version: 2.3
Name: donnes-des-sous-nawel
Version: 0.1.1
Summary: Add your description here
Author: NawelMera
Author-email: NawelMera <nawel.merabet@ig2i.centralelille.fr>
Requires-Dist: httpx>=0.28.1
Requires-Python: >=3.13
